init_maths_equation/__init__.py
init_maths_equation/__main__.py
init_maths_equation/chapters.py
init_maths_equation/choice_option.py
init_maths_equation/equation.py
init_maths_equation/main.py
init_maths_equation-0.1.0.dist-info/METADATA
init_maths_equation-0.1.0.dist-info/WHEEL
init_maths_equation-0.1.0.dist-info/entry_points.txt
init_maths_equation-0.1.0.dist-info/RECORD
